pydlt/__init__.py
pydlt/control/__init__.py
pydlt/control/service_id.py
pydlt/file.py
pydlt/header.py
pydlt/message.py
pydlt/payload.py
pydlt-0.3.5.dist-info/LICENSE
pydlt-0.3.5.dist-info/METADATA
pydlt-0.3.5.dist-info/WHEEL
pydlt-0.3.5.dist-info/RECORD
