Metadata-Version: 2.3
Name: pydlt
Version: 0.3.5
Summary: A pyre-python library to handle AUTOSAR DLT.
License: MIT
Author: Miki, Hiromitsu
Author-email: mikiepure+dev@gmail.com
Requires-Python: >=3.8
Classifier: License :: OSI Approved :: MIT License
Classifier: Programming Language :: Python :: 3
Classifier: Programming Language :: Python :: 3.8
Classifier: Programming Language :: Python :: 3.9
Classifier: Programming Language :: Python :: 3.10
Classifier: Programming Language :: Python :: 3.11
Classifier: Programming Language :: Python :: 3.12
Classifier: Programming Language :: Python :: 3.13
Project-URL: Homepage, https://mikiepure.github.io/
Project-URL: Repository, https://github.com/mikiepure/pydlt
